[
  {
    "direction": "Flat", 
    "noise": 1, 
    "sysTime": "2016-01-25T18:05:09.446-0800", 
    "xDrip_calculated_value": 123, 
    "xDrip_raw": 141, 
    "dateString": "2016-01-25T18:05:09.446-0800", 
    "sgv": 123, 
    "date": 1453773909446, 
    "xDrip_filtered": 140, 
    "xDrip_age_adjusted_raw_value": 141, 
    "unfiltered": 141000, 
    "rssi": 100, 
    "device": "xDrip-DexcomShare", 
    "filtered": 140000, 
    "xDrip_calculated_current_slope": 6.6728056478627e-06, 
    "_id": "56a6d48a07f60885b3444437", 
    "type": "sgv"
  }, 
  {
    "direction": "Flat", 
    "noise": 1, 
    "sysTime": "2016-01-25T18:00:09.722-0800", 
    "xDrip_calculated_value": 121, 
    "xDrip_raw": 140, 
    "dateString": "2016-01-25T18:00:09.722-0800", 
    "sgv": 121, 
    "date": 1453773609722, 
    "xDrip_filtered": 139, 
    "xDrip_age_adjusted_raw_value": 140, 
    "unfiltered": 140000, 
    "rssi": 100, 
    "device": "xDrip-DexcomShare", 
    "filtered": 139000, 
    "xDrip_calculated_current_slope": 3.334066828035501e-06, 
    "_id": "56a6d33e07f60885b3444435", 
    "type": "sgv"
  }, 
  {
    "direction": "Flat", 
    "noise": 1, 
    "sysTime": "2016-01-25T17:55:09.788-0800", 
    "xDrip_calculated_value": 120, 
    "xDrip_raw": 139, 
    "dateString": "2016-01-25T17:55:09.788-0800", 
    "sgv": 120, 
    "date": 1453773309788, 
    "xDrip_filtered": 139, 
    "xDrip_age_adjusted_raw_value": 139, 
    "unfiltered": 139000, 
    "rssi": 100, 
    "device": "xDrip-DexcomShare", 
    "filtered": 139000, 
    "xDrip_calculated_current_slope": -3.3292827060409835e-06, 
    "_id": "56a6d21207f60885b3444432", 
    "type": "sgv"
  }, 
  {
    "direction": "Flat", 
    "noise": 1, 
    "sysTime": "2016-01-25T17:50:09.423-0800", 
    "xDrip_calculated_value": 121, 
    "xDrip_raw": 140, 
    "dateString": "2016-01-25T17:50:09.423-0800", 
    "sgv": 121, 
    "date": 1453773009423, 
    "xDrip_filtered": 138, 
    "xDrip_age_adjusted_raw_value": 140, 
    "unfiltered": 140000, 
    "rssi": 100, 
    "device": "xDrip-DexcomShare", 
    "filtered": 138000, 
    "xDrip_calculated_current_slope": 1.0002200484106503e-05, 
    "_id": "56a6d10807f60885b3444430", 
    "type": "sgv"
  }, 
  {
    "direction": "Flat", 
    "noise": 1, 
    "sysTime": "2016-01-25T17:45:09.489-0800", 
    "xDrip_calculated_value": 118, 
    "xDrip_raw": 138, 
    "dateString": "2016-01-25T17:45:09.489-0800", 
    "sgv": 118, 
    "date": 1453772709489, 
    "xDrip_filtered": 138, 
    "xDrip_age_adjusted_raw_value": 138, 
    "unfiltered": 138000, 
    "rssi": 100, 
    "device": "xDrip-DexcomShare", 
    "filtered": 138000, 
    "xDrip_calculated_current_slope": -3.3353345340537656e-06, 
    "_id": "56a6cfbc07f60885b344442d", 
    "type": "sgv"
  }, 
  {
    "direction": "Flat", 
    "noise": 1, 
    "sysTime": "2016-01-25T17:40:09.669-0800", 
    "xDrip_calculated_value": 119, 
    "xDrip_raw": 138, 
    "dateString": "2016-01-25T17:40:09.669-0800", 
    "sgv": 119, 
    "date": 1453772409669, 
    "xDrip_filtered": 136, 
    "xDrip_age_adjusted_raw_value": 138, 
    "unfiltered": 138000, 
    "rssi": 100, 
    "device": "xDrip-DexcomShare", 
    "filtered": 136000, 
    "xDrip_calculated_current_slope": 0, 
    "_id": "56a6ce9007f60885b344442c", 
    "type": "sgv"
  }, 
  {
    "direction": "Flat", 
    "noise": 1, 
    "sysTime": "2016-01-25T17:35:09.501-0800", 
    "xDrip_calculated_value": 119, 
    "xDrip_raw": 138, 
    "dateString": "2016-01-25T17:35:09.501-0800", 
    "sgv": 119, 
    "date": 1453772109501, 
    "xDrip_filtered": 135, 
    "xDrip_age_adjusted_raw_value": 138, 
    "unfiltered": 138000, 
    "rssi": 100, 
    "device": "xDrip-DexcomShare", 
    "filtered": 135000, 
    "xDrip_calculated_current_slope": 1.0019605027169829e-05, 
    "_id": "56a6cd8307f60885b344442b", 
    "type": "sgv"
  }, 
  {
    "direction": "Flat", 
    "noise": 1, 
    "sysTime": "2016-01-25T17:30:10.088-0800", 
    "xDrip_calculated_value": 116, 
    "xDrip_raw": 136, 
    "dateString": "2016-01-25T17:30:10.088-0800", 
    "sgv": 116, 
    "date": 1453771810088, 
    "xDrip_filtered": 135, 
    "xDrip_age_adjusted_raw_value": 136, 
    "unfiltered": 136000, 
    "rssi": 100, 
    "device": "xDrip-DexcomShare", 
    "filtered": 135000, 
    "xDrip_calculated_current_slope": 3.334089060186976e-06, 
    "_id": "56a6cc3707f60885b3444429", 
    "type": "sgv"
  }, 
  {
    "direction": "Flat", 
    "noise": 1, 
    "sysTime": "2016-01-25T17:25:10.156-0800", 
    "xDrip_calculated_value": 115, 
    "xDrip_raw": 135, 
    "dateString": "2016-01-25T17:25:10.156-0800", 
    "sgv": 115, 
    "date": 1453771510156, 
    "xDrip_filtered": 135, 
    "xDrip_age_adjusted_raw_value": 135, 
    "unfiltered": 135000, 
    "rssi": 100, 
    "device": "xDrip-DexcomShare", 
    "filtered": 135000, 
    "xDrip_calculated_current_slope": 0, 
    "_id": "56a6cb0b07f60885b3444426", 
    "type": "sgv"
  }, 
  {
    "direction": "Flat", 
    "noise": 1, 
    "sysTime": "2016-01-25T17:20:10.148-0800", 
    "xDrip_calculated_value": 115, 
    "xDrip_raw": 135, 
    "dateString": "2016-01-25T17:20:10.148-0800", 
    "sgv": 115, 
    "date": 1453771210148, 
    "xDrip_filtered": 136, 
    "xDrip_age_adjusted_raw_value": 135, 
    "unfiltered": 135000, 
    "rssi": 100, 
    "device": "xDrip-DexcomShare", 
    "filtered": 136000, 
    "xDrip_calculated_current_slope": 0, 
    "_id": "56a6c9ff07f60885b3444424", 
    "type": "sgv"
  }
]