[
  {
    "direction": "Flat", 
    "noise": 1, 
    "sysTime": "2016-02-16T03:02:08.731-0800", 
    "xDrip_calculated_value": 118, 
    "xDrip_raw": 154, 
    "dateString": "2016-02-16T03:02:08.731-0800", 
    "sgv": 118, 
    "date": 1455620528731, 
    "xDrip_filtered": 155, 
    "xDrip_age_adjusted_raw_value": 154, 
    "unfiltered": 154000, 
    "rssi": 100, 
    "device": "xDrip-DexcomShare", 
    "filtered": 155000, 
    "xDrip_calculated_current_slope": -3.3261820419431555e-06, 
    "_id": "56c301c407f60885b3447b04", 
    "type": "sgv"
  }, 
  {
    "direction": "Flat", 
    "noise": 1, 
    "sysTime": "2016-02-16T02:57:08.086-0800", 
    "xDrip_calculated_value": 119, 
    "xDrip_raw": 155, 
    "dateString": "2016-02-16T02:57:08.086-0800", 
    "sgv": 119, 
    "date": 1455620228086, 
    "xDrip_filtered": 156, 
    "xDrip_age_adjusted_raw_value": 155, 
    "unfiltered": 155000, 
    "rssi": 100, 
    "device": "xDrip-DexcomShare", 
    "filtered": 156000, 
    "xDrip_calculated_current_slope": -3.340883730564409e-06, 
    "_id": "56c300c107f60885b3447b03", 
    "type": "sgv"
  }, 
  {
    "direction": "Flat", 
    "noise": 1, 
    "sysTime": "2016-02-16T02:52:08.764-0800", 
    "xDrip_calculated_value": 120, 
    "xDrip_raw": 156, 
    "dateString": "2016-02-16T02:52:08.764-0800", 
    "sgv": 120, 
    "date": 1455619928764, 
    "xDrip_filtered": 158, 
    "xDrip_age_adjusted_raw_value": 156, 
    "unfiltered": 156000, 
    "rssi": 100, 
    "device": "xDrip-DexcomShare", 
    "filtered": 158000, 
    "xDrip_calculated_current_slope": -6.6666444445185185e-06, 
    "_id": "56c2ff7307f60885b3447aff", 
    "type": "sgv"
  }, 
  {
    "direction": "Flat", 
    "noise": 1, 
    "sysTime": "2016-02-16T02:47:08.763-0800", 
    "xDrip_calculated_value": 122, 
    "xDrip_raw": 158, 
    "dateString": "2016-02-16T02:47:08.763-0800", 
    "sgv": 122, 
    "date": 1455619628763, 
    "xDrip_filtered": 162, 
    "xDrip_age_adjusted_raw_value": 158, 
    "unfiltered": 158000, 
    "rssi": 100, 
    "device": "xDrip-DexcomShare", 
    "filtered": 162000, 
    "xDrip_calculated_current_slope": -3.3262041690643057e-06, 
    "_id": "56c2fe4607f60885b3447afe", 
    "type": "sgv"
  }, 
  {
    "direction": "Flat", 
    "noise": 1, 
    "sysTime": "2016-02-16T02:42:08.120-0800", 
    "xDrip_calculated_value": 123, 
    "xDrip_raw": 160, 
    "dateString": "2016-02-16T02:42:08.120-0800", 
    "sgv": 123, 
    "date": 1455619328120, 
    "xDrip_filtered": 168, 
    "xDrip_age_adjusted_raw_value": 160, 
    "unfiltered": 160000, 
    "rssi": 100, 
    "device": "xDrip-DexcomShare", 
    "filtered": 168000, 
    "xDrip_calculated_current_slope": -1.3361704686283877e-05, 
    "_id": "56c2fd3c07f60885b3447afc", 
    "type": "sgv"
  }, 
  {
    "direction": "Flat", 
    "noise": 1, 
    "sysTime": "2016-02-16T02:37:08.757-0800", 
    "xDrip_calculated_value": 127, 
    "xDrip_raw": 164, 
    "dateString": "2016-02-16T02:37:08.757-0800", 
    "sgv": 127, 
    "date": 1455619028757, 
    "xDrip_filtered": 174, 
    "xDrip_age_adjusted_raw_value": 164, 
    "unfiltered": 164000, 
    "rssi": 100, 
    "device": "xDrip-DexcomShare", 
    "filtered": 174000, 
    "xDrip_calculated_current_slope": -1.9977758095986467e-05, 
    "_id": "56c2fbee07f60885b3447afa", 
    "type": "sgv"
  }, 
  {
    "direction": "Flat", 
    "noise": 1, 
    "sysTime": "2016-02-16T02:32:08.423-0800", 
    "xDrip_calculated_value": 133, 
    "xDrip_raw": 170, 
    "dateString": "2016-02-16T02:32:08.423-0800", 
    "sgv": 133, 
    "date": 1455618728423, 
    "xDrip_filtered": 179, 
    "xDrip_age_adjusted_raw_value": 170, 
    "unfiltered": 170000, 
    "rssi": 100, 
    "device": "xDrip-DexcomShare", 
    "filtered": 179000, 
    "xDrip_calculated_current_slope": -1.9966257025626692e-05, 
    "_id": "56c2fabc07f60885b3447af8", 
    "type": "sgv"
  }, 
  {
    "direction": "Flat", 
    "noise": 1, 
    "sysTime": "2016-02-16T02:27:07.916-0800", 
    "xDrip_calculated_value": 139, 
    "xDrip_raw": 177, 
    "dateString": "2016-02-16T02:27:07.916-0800", 
    "sgv": 139, 
    "date": 1455618427916, 
    "xDrip_filtered": 181, 
    "xDrip_age_adjusted_raw_value": 177, 
    "unfiltered": 177000, 
    "rssi": 100, 
    "device": "xDrip-DexcomShare", 
    "filtered": 181000, 
    "xDrip_calculated_current_slope": -9.975095511539523e-06, 
    "_id": "56c2f98f07f60885b3447af6", 
    "type": "sgv"
  }, 
  {
    "direction": "Flat", 
    "noise": 1, 
    "sysTime": "2016-02-16T02:22:07.167-0800", 
    "xDrip_calculated_value": 142, 
    "xDrip_raw": 181, 
    "dateString": "2016-02-16T02:22:07.167-0800", 
    "sgv": 142, 
    "date": 1455618127167, 
    "xDrip_filtered": 183, 
    "xDrip_age_adjusted_raw_value": 181, 
    "unfiltered": 181000, 
    "rssi": 100, 
    "device": "xDrip-DexcomShare", 
    "filtered": 183000, 
    "xDrip_calculated_current_slope": -1.0020843354176688e-05, 
    "_id": "56c2f86407f60885b3447af5", 
    "type": "sgv"
  }, 
  {
    "direction": "Flat", 
    "noise": 1, 
    "sysTime": "2016-02-16T02:17:07.791-0800", 
    "xDrip_calculated_value": 145, 
    "xDrip_raw": 183, 
    "dateString": "2016-02-16T02:17:07.791-0800", 
    "sgv": 145, 
    "date": 1455617827791, 
    "xDrip_filtered": 185, 
    "xDrip_age_adjusted_raw_value": 183, 
    "unfiltered": 183000, 
    "rssi": 100, 
    "device": "xDrip-DexcomShare", 
    "filtered": 185000, 
    "xDrip_calculated_current_slope": -3.3262373602980307e-06, 
    "_id": "56c2f73d07f60885b3447af4", 
    "type": "sgv"
  }
]