[
  {
    "direction": "FortyFiveUp", 
    "noise": 1, 
    "sysTime": "2016-01-23T02:18:44.527-0800", 
    "xDrip_calculated_value": 147, 
    "xDrip_raw": 166, 
    "dateString": "2016-01-23T02:18:44.527-0800", 
    "sgv": 147, 
    "date": 1453544324527, 
    "xDrip_filtered": 157, 
    "xDrip_age_adjusted_raw_value": 166, 
    "unfiltered": 166000, 
    "rssi": 100, 
    "device": "xDrip-DexcomShare", 
    "filtered": 157000, 
    "xDrip_calculated_current_slope": 2.0007602889097857e-05, 
    "_id": "56a3539907f60885b3443f0f", 
    "type": "sgv"
  }, 
  {
    "direction": "SingleUp", 
    "noise": 1, 
    "sysTime": "2016-01-23T02:13:44.641-0800", 
    "xDrip_calculated_value": 141, 
    "xDrip_raw": 160, 
    "dateString": "2016-01-23T02:13:44.641-0800", 
    "sgv": 141, 
    "date": 1453544024641, 
    "xDrip_filtered": 148, 
    "xDrip_age_adjusted_raw_value": 160, 
    "unfiltered": 160000, 
    "rssi": 100, 
    "device": "xDrip-DexcomShare", 
    "filtered": 148000, 
    "xDrip_calculated_current_slope": 2.3369868227328726e-05, 
    "_id": "56a3527107f60885b3443f0e", 
    "type": "sgv"
  }, 
  {
    "direction": "SingleUp", 
    "noise": 1, 
    "sysTime": "2016-01-23T02:08:45.110-0800", 
    "xDrip_calculated_value": 134, 
    "xDrip_raw": 153, 
    "dateString": "2016-01-23T02:08:45.110-0800", 
    "sgv": 134, 
    "date": 1453543725110, 
    "xDrip_filtered": 135, 
    "xDrip_age_adjusted_raw_value": 153, 
    "unfiltered": 153000, 
    "rssi": 100, 
    "device": "xDrip-DexcomShare", 
    "filtered": 135000, 
    "xDrip_calculated_current_slope": 3.668904698532772e-05, 
    "_id": "56a3516107f60885b3443f0d", 
    "type": "sgv"
  }, 
  {
    "direction": "SingleUp", 
    "noise": 1, 
    "sysTime": "2016-01-23T02:03:45.293-0800", 
    "xDrip_calculated_value": 123, 
    "xDrip_raw": 143, 
    "dateString": "2016-01-23T02:03:45.293-0800", 
    "sgv": 123, 
    "date": 1453543425293, 
    "xDrip_filtered": 121, 
    "xDrip_age_adjusted_raw_value": 143, 
    "unfiltered": 143000, 
    "rssi": 100, 
    "device": "xDrip-DexcomShare", 
    "filtered": 121000, 
    "xDrip_calculated_current_slope": 3.9993201155803516e-05, 
    "_id": "56a3501907f60885b3443f0c", 
    "type": "sgv"
  }, 
  {
    "direction": "SingleUp", 
    "noise": 1, 
    "sysTime": "2016-01-23T01:58:45.242-0800", 
    "xDrip_calculated_value": 111, 
    "xDrip_raw": 131, 
    "dateString": "2016-01-23T01:58:45.242-0800", 
    "sgv": 111, 
    "date": 1453543125242, 
    "xDrip_filtered": 109, 
    "xDrip_age_adjusted_raw_value": 131, 
    "unfiltered": 131000, 
    "rssi": 100, 
    "device": "xDrip-DexcomShare", 
    "filtered": 109000, 
    "xDrip_calculated_current_slope": 4.9992667742064494e-05, 
    "_id": "56a34eeb07f60885b3443f0a", 
    "type": "sgv"
  }, 
  {
    "direction": "FortyFiveUp", 
    "noise": 1, 
    "sysTime": "2016-01-23T01:53:45.198-0800", 
    "xDrip_calculated_value": 96, 
    "xDrip_raw": 116, 
    "dateString": "2016-01-23T01:53:45.198-0800", 
    "sgv": 96, 
    "date": 1453542825198, 
    "xDrip_filtered": 101, 
    "xDrip_age_adjusted_raw_value": 116, 
    "unfiltered": 116000, 
    "rssi": 100, 
    "device": "xDrip-DexcomShare", 
    "filtered": 101000, 
    "xDrip_calculated_current_slope": 4.3280963367658466e-05, 
    "_id": "56a34ddd07f60885b3443f08", 
    "type": "sgv"
  }, 
  {
    "direction": "Flat", 
    "noise": 1, 
    "sysTime": "2016-01-23T01:48:44.835-0800", 
    "xDrip_calculated_value": 83, 
    "xDrip_raw": 104, 
    "dateString": "2016-01-23T01:48:44.835-0800", 
    "sgv": 83, 
    "date": 1453542524835, 
    "xDrip_filtered": 97, 
    "xDrip_age_adjusted_raw_value": 104, 
    "unfiltered": 104000, 
    "rssi": 100, 
    "device": "xDrip-DexcomShare", 
    "filtered": 97000, 
    "xDrip_calculated_current_slope": 2.333862342130883e-05, 
    "_id": "56a34c9207f60885b3443f06", 
    "type": "sgv"
  }, 
  {
    "direction": "Flat", 
    "noise": 1, 
    "sysTime": "2016-01-23T01:43:44.903-0800", 
    "xDrip_calculated_value": 76, 
    "xDrip_raw": 97, 
    "dateString": "2016-01-23T01:43:44.903-0800", 
    "sgv": 76, 
    "date": 1453542224903, 
    "xDrip_filtered": 96, 
    "xDrip_age_adjusted_raw_value": 97, 
    "unfiltered": 97000, 
    "rssi": 100, 
    "device": "xDrip-DexcomShare", 
    "filtered": 96000, 
    "xDrip_calculated_current_slope": 3.334066828035501e-06, 
    "_id": "56a34b6507f60885b3443f04", 
    "type": "sgv"
  }, 
  {
    "direction": "Flat", 
    "noise": 1, 
    "sysTime": "2016-01-23T01:38:44.969-0800", 
    "xDrip_calculated_value": 75, 
    "xDrip_raw": 96, 
    "dateString": "2016-01-23T01:38:44.969-0800", 
    "sgv": 75, 
    "date": 1453541924969, 
    "xDrip_filtered": 96, 
    "xDrip_age_adjusted_raw_value": 96, 
    "unfiltered": 96000, 
    "rssi": 100, 
    "device": "xDrip-DexcomShare", 
    "filtered": 96000, 
    "xDrip_calculated_current_slope": 0, 
    "_id": "56a34a5807f60885b3443f02", 
    "type": "sgv"
  }, 
  {
    "direction": "Flat", 
    "noise": 1, 
    "sysTime": "2016-01-23T01:33:44.147-0800", 
    "xDrip_calculated_value": 75, 
    "xDrip_raw": 96, 
    "dateString": "2016-01-23T01:33:44.147-0800", 
    "sgv": 75, 
    "date": 1453541624147, 
    "xDrip_filtered": 97, 
    "xDrip_age_adjusted_raw_value": 96, 
    "unfiltered": 96000, 
    "rssi": 100, 
    "device": "xDrip-DexcomShare", 
    "filtered": 97000, 
    "xDrip_calculated_current_slope": -3.3389650543917407e-06, 
    "_id": "56a3490f07f60885b3443eff", 
    "type": "sgv"
  }
]