[
  {
    "direction": "DoubleUp", 
    "noise": 1, 
    "sysTime": "2016-01-20T07:58:54.783-0800", 
    "xDrip_calculated_value": 146, 
    "xDrip_raw": 145, 
    "dateString": "2016-01-20T07:58:54.783-0800", 
    "sgv": 146, 
    "date": 1453305534783, 
    "xDrip_filtered": 121, 
    "xDrip_age_adjusted_raw_value": 145, 
    "unfiltered": 145000, 
    "rssi": 100, 
    "device": "xDrip-DexcomShare", 
    "filtered": 121000, 
    "xDrip_calculated_current_slope": 7.02223708409965e-05, 
    "_id": "569faed507f60885b344399c", 
    "type": "sgv"
  }, 
  {
    "direction": "SingleUp", 
    "noise": 1, 
    "sysTime": "2016-01-20T07:53:55.733-0800", 
    "xDrip_calculated_value": 125, 
    "xDrip_raw": 129, 
    "dateString": "2016-01-20T07:53:55.733-0800", 
    "sgv": 125, 
    "date": 1453305235733, 
    "xDrip_filtered": 108, 
    "xDrip_age_adjusted_raw_value": 129, 
    "unfiltered": 129000, 
    "rssi": 100, 
    "device": "xDrip-DexcomShare", 
    "filtered": 108000, 
    "xDrip_calculated_current_slope": 4.9837529653330144e-05, 
    "_id": "569fadc707f60885b344399b", 
    "type": "sgv"
  }, 
  {
    "direction": "FortyFiveUp", 
    "noise": 1, 
    "sysTime": "2016-01-20T07:48:54.755-0800", 
    "xDrip_calculated_value": 110, 
    "xDrip_raw": 117, 
    "dateString": "2016-01-20T07:48:54.755-0800", 
    "sgv": 110, 
    "date": 1453304934755, 
    "xDrip_filtered": 99, 
    "xDrip_age_adjusted_raw_value": 117, 
    "unfiltered": 117000, 
    "rssi": 100, 
    "device": "xDrip-DexcomShare", 
    "filtered": 99000, 
    "xDrip_calculated_current_slope": 5.3405252406574185e-05, 
    "_id": "569fac7c07f60885b344399a", 
    "type": "sgv"
  }, 
  {
    "direction": "Flat", 
    "noise": 1, 
    "sysTime": "2016-01-20T07:43:55.159-0800", 
    "xDrip_calculated_value": 94, 
    "xDrip_raw": 104, 
    "dateString": "2016-01-20T07:43:55.159-0800", 
    "sgv": 94, 
    "date": 1453304635159, 
    "xDrip_filtered": 95, 
    "xDrip_age_adjusted_raw_value": 104, 
    "unfiltered": 104000, 
    "rssi": 100, 
    "device": "xDrip-DexcomShare", 
    "filtered": 95000, 
    "xDrip_calculated_current_slope": 3.3323225288329204e-05, 
    "_id": "569fab5007f60885b3443999", 
    "type": "sgv"
  }, 
  {
    "direction": "Flat", 
    "noise": 1, 
    "sysTime": "2016-01-20T07:38:55.068-0800", 
    "xDrip_calculated_value": 84, 
    "xDrip_raw": 95, 
    "dateString": "2016-01-20T07:38:55.068-0800", 
    "sgv": 84, 
    "date": 1453304335068, 
    "xDrip_filtered": 93, 
    "xDrip_age_adjusted_raw_value": 95, 
    "unfiltered": 95000, 
    "rssi": 100, 
    "device": "xDrip-DexcomShare", 
    "filtered": 93000, 
    "xDrip_calculated_current_slope": 1.001117915005089e-05, 
    "_id": "569faa1e07f60885b3443996", 
    "type": "sgv"
  }, 
  {
    "direction": "Flat", 
    "noise": 1, 
    "sysTime": "2016-01-20T07:33:55.403-0800", 
    "xDrip_calculated_value": 81, 
    "xDrip_raw": 93, 
    "dateString": "2016-01-20T07:33:55.403-0800", 
    "sgv": 81, 
    "date": 1453304035403, 
    "xDrip_filtered": 94, 
    "xDrip_age_adjusted_raw_value": 93, 
    "unfiltered": 93000, 
    "rssi": 100, 
    "device": "xDrip-DexcomShare", 
    "filtered": 94000, 
    "xDrip_calculated_current_slope": -3.3345004084763e-06, 
    "_id": "569fa8f507f60885b3443994", 
    "type": "sgv"
  }, 
  {
    "direction": "Flat", 
    "noise": 1, 
    "sysTime": "2016-01-20T07:28:55.508-0800", 
    "xDrip_calculated_value": 82, 
    "xDrip_raw": 94, 
    "dateString": "2016-01-20T07:28:55.508-0800", 
    "sgv": 82, 
    "date": 1453303735508, 
    "xDrip_filtered": 96, 
    "xDrip_age_adjusted_raw_value": 94, 
    "unfiltered": 94000, 
    "rssi": 100, 
    "device": "xDrip-DexcomShare", 
    "filtered": 96000, 
    "xDrip_calculated_current_slope": 0, 
    "_id": "569fa7cc07f60885b3443993", 
    "type": "sgv"
  }, 
  {
    "direction": "Flat", 
    "noise": 1, 
    "sysTime": "2016-01-20T07:23:55.283-0800", 
    "xDrip_calculated_value": 82, 
    "xDrip_raw": 94, 
    "dateString": "2016-01-20T07:23:55.283-0800", 
    "sgv": 82, 
    "date": 1453303435283, 
    "xDrip_filtered": 100, 
    "xDrip_age_adjusted_raw_value": 94, 
    "unfiltered": 94000, 
    "rssi": 100, 
    "device": "xDrip-DexcomShare", 
    "filtered": 100000, 
    "xDrip_calculated_current_slope": -1.667628332338315e-05, 
    "_id": "569fa69f07f60885b3443991", 
    "type": "sgv"
  }, 
  {
    "direction": "FortyFiveDown", 
    "noise": 1, 
    "sysTime": "2016-01-20T07:18:55.456-0800", 
    "xDrip_calculated_value": 87, 
    "xDrip_raw": 98, 
    "dateString": "2016-01-20T07:18:55.456-0800", 
    "sgv": 87, 
    "date": 1453303135456, 
    "xDrip_filtered": 104, 
    "xDrip_age_adjusted_raw_value": 98, 
    "unfiltered": 98000, 
    "rssi": 100, 
    "device": "xDrip-DexcomShare", 
    "filtered": 104000, 
    "xDrip_calculated_current_slope": -1.335109028341027e-05, 
    "_id": "569fa59307f60885b344398e", 
    "type": "sgv"
  }, 
  {
    "direction": "FortyFiveDown", 
    "noise": 1, 
    "sysTime": "2016-01-20T07:13:55.855-0800", 
    "xDrip_calculated_value": 91, 
    "xDrip_raw": 101, 
    "dateString": "2016-01-20T07:13:55.855-0800", 
    "sgv": 91, 
    "date": 1453302835855, 
    "xDrip_filtered": 109, 
    "xDrip_age_adjusted_raw_value": 101, 
    "unfiltered": 101000, 
    "rssi": 100, 
    "device": "xDrip-DexcomShare", 
    "filtered": 109000, 
    "xDrip_calculated_current_slope": -1.99620056492476e-05, 
    "_id": "569fa44707f60885b344398d", 
    "type": "sgv"
  }
]