[
  {
    "trend_arrow": "FLAT", 
    "system_time": "2016-01-23T19:35:02", 
    "display_time": "2016-01-23T12:33:31", 
    "glucose": 116
  }, 
  {
    "trend_arrow": "FLAT", 
    "system_time": "2016-01-23T19:30:02", 
    "display_time": "2016-01-23T12:28:31", 
    "glucose": 120
  }, 
  {
    "trend_arrow": "FLAT", 
    "system_time": "2016-01-23T19:25:02", 
    "display_time": "2016-01-23T12:23:31", 
    "glucose": 120
  }, 
  {
    "trend_arrow": "FLAT", 
    "system_time": "2016-01-23T19:20:02", 
    "display_time": "2016-01-23T12:18:31", 
    "glucose": 123
  }, 
  {
    "trend_arrow": "FLAT", 
    "system_time": "2016-01-23T19:15:02", 
    "display_time": "2016-01-23T12:13:31", 
    "glucose": 126
  }
]