[
  {
    "filtered": 94000, 
    "direction": "Flat", 
    "noise": 1, 
    "raw": 66, 
    "type": "sgv", 
    "_id": "5708ec5e65110bbfc192b2ab", 
    "sysTime": "2016-04-09T04:48:36.679-0700", 
    "dateString": "2016-04-09T04:48:36.679-0700", 
    "sgv": 68, 
    "device": "xDrip-DexcomShare", 
    "xDrip_filtered": 94, 
    "unfiltered": 92000, 
    "xDrip_raw": 92, 
    "date": 1460202516679, 
    "rssi": 100, 
    "xDrip_calculated_current_slope": -9.991174462558074e-06, 
    "xDrip_age_adjusted_raw_value": 92, 
    "xDrip_calculated_value": 68
  }, 
  {
    "filtered": 95000, 
    "direction": "Flat", 
    "noise": 1, 
    "raw": 70, 
    "type": "sgv", 
    "_id": "5708eb0965110bbfc192b2aa", 
    "sysTime": "2016-04-09T04:43:36.414-0700", 
    "dateString": "2016-04-09T04:43:36.414-0700", 
    "sgv": 71, 
    "device": "xDrip-DexcomShare", 
    "xDrip_filtered": 95, 
    "unfiltered": 94000, 
    "xDrip_raw": 94, 
    "date": 1460202216414, 
    "rssi": 100, 
    "xDrip_calculated_current_slope": -1.335104572065607e-05, 
    "xDrip_age_adjusted_raw_value": 94, 
    "xDrip_calculated_value": 71
  }, 
  {
    "filtered": 98000, 
    "direction": "Flat", 
    "noise": 1, 
    "raw": 73, 
    "type": "sgv", 
    "_id": "5708ea0565110bbfc192b2a7", 
    "sysTime": "2016-04-09T04:38:36.812-0700", 
    "dateString": "2016-04-09T04:38:36.812-0700", 
    "sgv": 75, 
    "device": "xDrip-DexcomShare", 
    "xDrip_filtered": 98, 
    "unfiltered": 96000, 
    "xDrip_raw": 96, 
    "date": 1460201916812, 
    "rssi": 100, 
    "xDrip_calculated_current_slope": -9.988779271285257e-06, 
    "xDrip_age_adjusted_raw_value": 96, 
    "xDrip_calculated_value": 75
  }, 
  {
    "filtered": 101000, 
    "direction": "Flat", 
    "noise": 1, 
    "raw": 69, 
    "type": "sgv", 
    "_id": "5708e8b265110bbfc192b2a3", 
    "sysTime": "2016-04-09T04:33:36.475-0700", 
    "dateString": "2016-04-09T04:33:36.475-0700", 
    "sgv": 78, 
    "device": "xDrip-DexcomShare", 
    "xDrip_filtered": 101, 
    "unfiltered": 93000, 
    "xDrip_raw": 93, 
    "date": 1460201616475, 
    "rssi": 100, 
    "xDrip_calculated_current_slope": -2.670218056682054e-05, 
    "xDrip_age_adjusted_raw_value": 93, 
    "xDrip_calculated_value": 78
  }, 
  {
    "filtered": 104000, 
    "direction": "Flat", 
    "noise": 1, 
    "raw": 81, 
    "type": "sgv", 
    "_id": "5708e7ab65110bbfc192b2a2", 
    "sysTime": "2016-04-09T04:28:36.874-0700", 
    "dateString": "2016-04-09T04:28:36.874-0700", 
    "sgv": 86, 
    "device": "xDrip-DexcomShare", 
    "xDrip_filtered": 104, 
    "unfiltered": 100000, 
    "xDrip_raw": 100, 
    "date": 1460201316874, 
    "rssi": 100, 
    "xDrip_calculated_current_slope": -1.3321344123622073e-05, 
    "xDrip_age_adjusted_raw_value": 100, 
    "xDrip_calculated_value": 86
  }, 
  {
    "filtered": 107000, 
    "direction": "Flat", 
    "noise": 1, 
    "raw": 85, 
    "type": "sgv", 
    "_id": "5708e65965110bbfc192b2a1", 
    "sysTime": "2016-04-09T04:23:36.604-0700", 
    "dateString": "2016-04-09T04:23:36.604-0700", 
    "sgv": 90, 
    "device": "xDrip-DexcomShare", 
    "xDrip_filtered": 107, 
    "unfiltered": 103000, 
    "xDrip_raw": 103, 
    "date": 1460201016604, 
    "rssi": 100, 
    "xDrip_calculated_current_slope": -1.0009509033581903e-05, 
    "xDrip_age_adjusted_raw_value": 103, 
    "xDrip_calculated_value": 90
  }, 
  {
    "filtered": 109000, 
    "direction": "Flat", 
    "noise": 1, 
    "raw": 88, 
    "type": "sgv", 
    "_id": "5708e55265110bbfc192b29e", 
    "sysTime": "2016-04-09T04:18:36.889-0700", 
    "dateString": "2016-04-09T04:18:36.889-0700", 
    "sgv": 93, 
    "device": "xDrip-DexcomShare", 
    "xDrip_filtered": 109, 
    "unfiltered": 105000, 
    "xDrip_raw": 105, 
    "date": 1460200716889, 
    "rssi": 100, 
    "xDrip_calculated_current_slope": -9.987316108542152e-06, 
    "xDrip_age_adjusted_raw_value": 105, 
    "xDrip_calculated_value": 93
  }, 
  {
    "filtered": 112000, 
    "direction": "Flat", 
    "noise": 1, 
    "raw": 91, 
    "type": "sgv", 
    "_id": "5708e40065110bbfc192b29d", 
    "sysTime": "2016-04-09T04:13:36.508-0700", 
    "dateString": "2016-04-09T04:13:36.508-0700", 
    "sgv": 96, 
    "device": "xDrip-DexcomShare", 
    "xDrip_filtered": 112, 
    "unfiltered": 108000, 
    "xDrip_raw": 108, 
    "date": 1460200416508, 
    "rssi": 100, 
    "xDrip_calculated_current_slope": -1.0010644652146782e-05, 
    "xDrip_age_adjusted_raw_value": 108, 
    "xDrip_calculated_value": 96
  }, 
  {
    "filtered": 114000, 
    "direction": "Flat", 
    "noise": 1, 
    "raw": 94, 
    "type": "sgv", 
    "_id": "5708e2f765110bbfc192b29c", 
    "sysTime": "2016-04-09T04:08:36.827-0700", 
    "dateString": "2016-04-09T04:08:36.827-0700", 
    "sgv": 99, 
    "device": "xDrip-DexcomShare", 
    "xDrip_filtered": 114, 
    "unfiltered": 110000, 
    "xDrip_raw": 110, 
    "date": 1460200116827, 
    "rssi": 100, 
    "xDrip_calculated_current_slope": -1.3336356240747903e-05, 
    "xDrip_age_adjusted_raw_value": 110, 
    "xDrip_calculated_value": 99
  }, 
  {
    "filtered": 117000, 
    "direction": "Flat", 
    "noise": 1, 
    "raw": 98, 
    "type": "sgv", 
    "_id": "5708e1a665110bbfc192b299", 
    "sysTime": "2016-04-09T04:03:36.895-0700", 
    "dateString": "2016-04-09T04:03:36.895-0700", 
    "sgv": 103, 
    "device": "xDrip-DexcomShare", 
    "xDrip_filtered": 117, 
    "unfiltered": 113000, 
    "xDrip_raw": 113, 
    "date": 1460199816895, 
    "rssi": 100, 
    "xDrip_calculated_current_slope": -9.998400255959046e-06, 
    "xDrip_age_adjusted_raw_value": 113, 
    "xDrip_calculated_value": 103
  }
]