[
  {
    "trend_arrow": "FLAT", 
    "system_time": "2016-01-24T02:25:00", 
    "display_time": "2016-01-23T19:23:30", 
    "glucose": 128
  }, 
  {
    "trend_arrow": "FLAT", 
    "system_time": "2016-01-24T02:20:00", 
    "display_time": "2016-01-23T19:18:30", 
    "glucose": 134
  }, 
  {
    "trend_arrow": "FLAT", 
    "system_time": "2016-01-24T02:15:00", 
    "display_time": "2016-01-23T19:13:30", 
    "glucose": 136
  }, 
  {
    "trend_arrow": "FLAT", 
    "system_time": "2016-01-24T02:10:00", 
    "display_time": "2016-01-23T19:08:30", 
    "glucose": 135
  }, 
  {
    "trend_arrow": "FLAT", 
    "system_time": "2016-01-24T02:05:01", 
    "display_time": "2016-01-23T19:03:30", 
    "glucose": 132
  }
]