[
  {
    "direction": "Flat", 
    "noise": 1, 
    "sysTime": "2016-01-17T05:55:40.827-0800", 
    "xDrip_calculated_value": 82, 
    "xDrip_raw": 91, 
    "dateString": "2016-01-17T05:55:40.827-0800", 
    "sgv": 82, 
    "date": 1453038940827, 
    "xDrip_filtered": 82, 
    "xDrip_age_adjusted_raw_value": 91, 
    "unfiltered": 91000, 
    "rssi": 100, 
    "device": "xDrip-DexcomShare", 
    "filtered": 82000, 
    "xDrip_calculated_current_slope": 3.3391099936223e-05, 
    "_id": "569b9d9007f60885b3443370", 
    "type": "sgv"
  }, 
  {
    "direction": "Flat", 
    "noise": 1, 
    "sysTime": "2016-01-17T05:50:41.346-0800", 
    "xDrip_calculated_value": 72, 
    "xDrip_raw": 83, 
    "dateString": "2016-01-17T05:50:41.346-0800", 
    "sgv": 72, 
    "date": 1453038641346, 
    "xDrip_filtered": 81, 
    "xDrip_age_adjusted_raw_value": 83, 
    "unfiltered": 83000, 
    "rssi": 100, 
    "device": "xDrip-DexcomShare", 
    "filtered": 81000, 
    "xDrip_calculated_current_slope": 1.666650000166665e-05, 
    "_id": "569b9c4507f60885b344336f", 
    "type": "sgv"
  }, 
  {
    "direction": "Flat", 
    "noise": 1, 
    "sysTime": "2016-01-17T05:45:41.343-0800", 
    "xDrip_calculated_value": 67, 
    "xDrip_raw": 80, 
    "dateString": "2016-01-17T05:45:41.343-0800", 
    "sgv": 67, 
    "date": 1453038341343, 
    "xDrip_filtered": 81, 
    "xDrip_age_adjusted_raw_value": 80, 
    "unfiltered": 80000, 
    "rssi": 100, 
    "device": "xDrip-DexcomShare", 
    "filtered": 81000, 
    "xDrip_calculated_current_slope": -3.3319561248017486e-06, 
    "_id": "569b9b1a07f60885b344336d", 
    "type": "sgv"
  }, 
  {
    "direction": "Flat", 
    "noise": 1, 
    "sysTime": "2016-01-17T05:40:41.219-0800", 
    "xDrip_calculated_value": 68, 
    "xDrip_raw": 81, 
    "dateString": "2016-01-17T05:40:41.219-0800", 
    "sgv": 68, 
    "date": 1453038041219, 
    "xDrip_filtered": 82, 
    "xDrip_age_adjusted_raw_value": 81, 
    "unfiltered": 81000, 
    "rssi": 100, 
    "device": "xDrip-DexcomShare", 
    "filtered": 82000, 
    "xDrip_calculated_current_slope": -3.334656080245164e-06, 
    "_id": "569b9a3f07f60885b344336a", 
    "type": "sgv"
  }, 
  {
    "direction": "Flat", 
    "noise": 1, 
    "sysTime": "2016-01-17T05:35:41.338-0800", 
    "xDrip_calculated_value": 69, 
    "xDrip_raw": 81, 
    "dateString": "2016-01-17T05:35:41.338-0800", 
    "sgv": 69, 
    "date": 1453037741338, 
    "xDrip_filtered": 83, 
    "xDrip_age_adjusted_raw_value": 81, 
    "unfiltered": 81000, 
    "rssi": 100, 
    "device": "xDrip-DexcomShare", 
    "filtered": 83000, 
    "xDrip_calculated_current_slope": -6.664023270769262e-06, 
    "_id": "569b98c107f60885b3443368", 
    "type": "sgv"
  }, 
  {
    "direction": "Flat", 
    "noise": 1, 
    "sysTime": "2016-01-17T05:30:41.219-0800", 
    "xDrip_calculated_value": 71, 
    "xDrip_raw": 83, 
    "dateString": "2016-01-17T05:30:41.219-0800", 
    "sgv": 71, 
    "date": 1453037441219, 
    "xDrip_filtered": 85, 
    "xDrip_age_adjusted_raw_value": 83, 
    "unfiltered": 83000, 
    "rssi": 100, 
    "device": "xDrip-DexcomShare", 
    "filtered": 85000, 
    "xDrip_calculated_current_slope": -3.3332888894814736e-06, 
    "_id": "569b979507f60885b3443366", 
    "type": "sgv"
  }, 
  {
    "direction": "Flat", 
    "noise": 1, 
    "sysTime": "2016-01-17T05:25:41.215-0800", 
    "xDrip_calculated_value": 72, 
    "xDrip_raw": 84, 
    "dateString": "2016-01-17T05:25:41.215-0800", 
    "sgv": 72, 
    "date": 1453037141215, 
    "xDrip_filtered": 87, 
    "xDrip_age_adjusted_raw_value": 84, 
    "unfiltered": 84000, 
    "rssi": 100, 
    "device": "xDrip-DexcomShare", 
    "filtered": 87000, 
    "xDrip_calculated_current_slope": -2.666631111585179e-05, 
    "_id": "569b968807f60885b3443364", 
    "type": "sgv"
  }, 
  {
    "direction": "Flat", 
    "noise": 1, 
    "sysTime": "2016-01-17T05:20:41.211-0800", 
    "xDrip_calculated_value": 80, 
    "xDrip_raw": 86, 
    "dateString": "2016-01-17T05:20:41.211-0800", 
    "sgv": 80, 
    "date": 1453036841211, 
    "xDrip_filtered": 89, 
    "xDrip_age_adjusted_raw_value": 86, 
    "unfiltered": 86000, 
    "rssi": 100, 
    "device": "xDrip-DexcomShare", 
    "filtered": 89000, 
    "xDrip_calculated_current_slope": -6.669378880744836e-06, 
    "_id": "569b953d07f60885b344335d", 
    "type": "sgv"
  }, 
  {
    "direction": "Flat", 
    "noise": 1, 
    "sysTime": "2016-01-17T05:15:41.333-0800", 
    "xDrip_calculated_value": 82, 
    "xDrip_raw": 88, 
    "dateString": "2016-01-17T05:15:41.333-0800", 
    "sgv": 82, 
    "date": 1453036541333, 
    "xDrip_filtered": 92, 
    "xDrip_age_adjusted_raw_value": 88, 
    "unfiltered": 88000, 
    "rssi": 100, 
    "device": "xDrip-DexcomShare", 
    "filtered": 92000, 
    "xDrip_calculated_current_slope": -6.655994888195926e-06, 
    "_id": "569b941107f60885b344335b", 
    "type": "sgv"
  }, 
  {
    "direction": "Flat", 
    "noise": 1, 
    "sysTime": "2016-01-17T05:10:40.852-0800", 
    "xDrip_calculated_value": 84, 
    "xDrip_raw": 90, 
    "dateString": "2016-01-17T05:10:40.852-0800", 
    "sgv": 84, 
    "date": 1453036240852, 
    "xDrip_filtered": 94, 
    "xDrip_age_adjusted_raw_value": 90, 
    "unfiltered": 90000, 
    "rssi": 100, 
    "device": "xDrip-DexcomShare", 
    "filtered": 94000, 
    "xDrip_calculated_current_slope": -9.999833336111065e-06, 
    "_id": "569b930307f60885b3443359", 
    "type": "sgv"
  }
]