{
  "pump": {
    "battery": {
      "status": "normal", 
      "voltage": 1.51
    }, 
    "status": {
      "status": "normal", 
      "timestamp": "2016-01-18T23:41:35.000Z", 
      "bolusing": false, 
      "suspended": false
    }, 
    "reservoir": 90.375, 
    "clock": "2016-01-18T15:38:49-08:00"
  }, 
  "openaps": {
    "suggested": {
      "bg": 148, 
      "temp": "absolute", 
      "snoozeBG": 105, 
      "timestamp": "2016-01-18T23:40:33.000Z", 
      "rate": 0.05, 
      "reason": "Eventual BG 68<110, setting 0.056U/hr", 
      "eventualBG": 68, 
      "duration": 30, 
      "mealAssist": "Off: Carbs: 0 Boluses: 0.3 Target: 115 Deviation: -11 BGI: -1.8", 
      "tick": -4
    }, 
    "iob": {
      "timestamp": "2016-01-18T23:40:32.000Z", 
      "bolussnooze": 0.271, 
      "basaliob": 0.476, 
      "iob": 0.768, 
      "activity": 0.004
    }, 
    "enacted": {
      "requested": {
        "duration": 30, 
        "rate": 0.05, 
        "temp": "absolute"
      }, 
      "bg": 148, 
      "temp": "absolute", 
      "snoozeBG": 105, 
      "timestamp": "2016-01-18T23:40:38.000Z", 
      "reason": "Eventual BG 68<110, setting 0.056U/hr", 
      "rate": 1.425, 
      "eventualBG": 68, 
      "recieved": false, 
      "duration": 0, 
      "mealAssist": "Off: Carbs: 0 Boluses: 0.3 Target: 115 Deviation: -11 BGI: -1.8", 
      "tick": -4
    }
  }
}