{
  "pump": {
    "battery": {
      "status": "normal", 
      "voltage": 1.46
    }, 
    "status": {
      "status": "normal", 
      "timestamp": "2016-01-24T17:02:00.000Z", 
      "bolusing": false, 
      "suspended": false
    }, 
    "reservoir": 126, 
    "clock": "2016-01-24T09:00:38-08:00"
  }, 
  "openaps": {
    "suggested": {
      "bg": 113, 
      "temp": "absolute", 
      "snoozeBG": 194, 
      "timestamp": "2016-01-24T17:00:23.000Z", 
      "rate": 2.1, 
      "reason": "Eventual BG 268>=135, adj. req. rate:2.5 to maxSafeBasal:2.1, temp 0<2.0999999999999996U/hr", 
      "eventualBG": 268, 
      "duration": 30, 
      "mealAssist": "On: Carbs: 40 Boluses: 0.2 Target: 107.5 Deviation: 74 BGI: -2.12", 
      "tick": "+60"
    }, 
    "iob": {
      "timestamp": "2016-01-24T17:00:22.000Z", 
      "bolussnooze": 0, 
      "basaliob": -0.096, 
      "iob": -0.075, 
      "activity": 0.0047
    }, 
    "enacted": {
      "bg": 113, 
      "temp": "absolute", 
      "snoozeBG": 194, 
      "recieved": true, 
      "reason": "Eventual BG 268>=135, adj. req. rate:2.5 to maxSafeBasal:2.1, temp 0<2.0999999999999996U/hr", 
      "rate": 2.1, 
      "eventualBG": 268, 
      "timestamp": "2016-01-24T17:00:41.000Z", 
      "duration": 30, 
      "mealAssist": "On: Carbs: 40 Boluses: 0.2 Target: 107.5 Deviation: 74 BGI: -2.12", 
      "tick": "+60"
    }
  }
}