{
  "device": "openaps://indy2", 
  "pump": {
    "battery": {
      "status": "normal", 
      "voltage": 1.57
    }, 
    "status": {
      "status": "normal", 
      "timestamp": "2016-04-11T10:39:36.000Z", 
      "bolusing": false, 
      "suspended": false
    }, 
    "reservoir": 181.675, 
    "clock": "2016-04-11T03:38:48-07:00"
  }, 
  "openaps": {
    "suggested": {
      "bg": 74, 
      "temp": "absolute", 
      "snoozeBG": 24, 
      "timestamp": "2016-04-11T10:40:36.000Z", 
      "reason": "BG 74<80, but 29m left and 0 ~ req 0U/hr: no action required", 
      "eventualBG": 24, 
      "mealAssist": "Off: Carbs: 0 Boluses: 0 Target: 115 Deviation: -61 BGI: 1.2", 
      "tick": -1
    }, 
    "iob": {
      "netbasalinsulin": -0.65, 
      "timestamp": "2016-04-11T10:40:35.000Z", 
      "activity": -0.003, 
      "basaliob": -0.142, 
      "hightempinsulin": 0.25, 
      "bolussnooze": 0, 
      "iob": -0.142
    }, 
    "enacted": {
      "bg": 75, 
      "temp": "absolute", 
      "snoozeBG": 10, 
      "recieved": true, 
      "reason": "BG 75<80", 
      "rate": 0, 
      "eventualBG": 10, 
      "timestamp": "2016-04-11T10:38:16.000Z", 
      "duration": 30, 
      "mealAssist": "Off: Carbs: 0 Boluses: 0 Target: 115 Deviation: -73 BGI: 1.24", 
      "tick": -21
    }
  }, 
  "mmtune": {
    "scanDetails": [
      [
        "916.540", 
        1, 
        -97
      ], 
      [
        "916.560", 
        5, 
        -79
      ], 
      [
        "916.580", 
        5, 
        -78
      ], 
      [
        "916.600", 
        5, 
        -78
      ], 
      [
        "916.620", 
        5, 
        -77
      ], 
      [
        "916.640", 
        5, 
        -77
      ], 
      [
        "916.660", 
        2, 
        -91
      ], 
      [
        "916.680", 
        2, 
        -92
      ]
    ], 
    "setFreq": 916.64, 
    "timestamp": "2016-04-11T10:39:19.000Z", 
    "usedDefault": false
  }
}